.travis.yml
CHANGES.txt
COPYRIGHT.txt
LICENSE.txt
MANIFEST.in
README.txt
bootstrap.py
buildout.cfg
setup.py
src/megrok/__init__.py
src/megrok.menu.egg-info/PKG-INFO
src/megrok.menu.egg-info/SOURCES.txt
src/megrok.menu.egg-info/dependency_links.txt
src/megrok.menu.egg-info/namespace_packages.txt
src/megrok.menu.egg-info/not-zip-safe
src/megrok.menu.egg-info/requires.txt
src/megrok.menu.egg-info/top_level.txt
src/megrok/menu/__init__.py
src/megrok/menu/component.py
src/megrok/menu/configure.zcml
src/megrok/menu/grokker.py
src/megrok/menu/meta.zcml
src/megrok/menu/tests/__init__.py
src/megrok/menu/tests/ftesting.zcml
src/megrok/menu/tests/test_functional.py
src/megrok/menu/tests/test_menu.py
src/megrok/menu/tests/test_order.py