Metadata-Version: 1.1
Name: megrok.menu
Version: 0.4.1
Summary: Grok extension to configure browser menus
Home-page: http://pypi.python.org/pypi/megrok.menu
Author: The Grok community
Author-email: grok-dev@zope.org
License: ZPL
Platform: UNKNOWN
Classifier: Programming Language :: Python
Classifier: Environment :: Web Environment
Classifier: Framework :: Zope3
Classifier: License :: OSI Approved :: Zope Public License
